pretwita/__init__.py
pretwita/constants.py
pretwita/patterns.py
pretwita/pretwita.py
pretwita-0.1.1.dist-info/LICENSE
pretwita-0.1.1.dist-info/METADATA
pretwita-0.1.1.dist-info/WHEEL
pretwita-0.1.1.dist-info/top_level.txt
pretwita-0.1.1.dist-info/RECORD
