Metadata-Version: 2.1
Name: pretwita
Version: 0.1.1
Summary: A text PREprocessor for TWeets in the ITAlian language
Home-page: https://github.com/andreafailla/pretwita
Author: Andrea Failla
Author-email: andrea.failla.ak@gmail.com
License: UNKNOWN
Keywords: nlp natural-language-processing twitter italian tweet-preprocessing
Platform: UNKNOWN
Classifier: Development Status :: 4 - Beta
Classifier: Programming Language :: Python :: 3
Classifier: License :: OSI Approved :: GNU General Public License v3 (GPLv3)
Classifier: Operating System :: OS Independent
Requires-Python: >=3.0
License-File: LICENSE
